lisacattools/__init__.py
lisacattools/_version.py
lisacattools/analyze.py
lisacattools/catalog.py
lisacattools/custom_logging.py
lisacattools/logging.conf
lisacattools/monitoring.py
lisacattools/utils.py
lisacattools/plugins/__init__.py
lisacattools/plugins/mbh.py
lisacattools/plugins/ucb.py
lisacattools-1.1.1.dist-info/LICENSE
lisacattools-1.1.1.dist-info/METADATA
lisacattools-1.1.1.dist-info/WHEEL
lisacattools-1.1.1.dist-info/top_level.txt
lisacattools-1.1.1.dist-info/RECORD
