Metadata-Version: 2.1
Name: lisacattools
Version: 1.1.1
Summary: A small example package for using LISA catalogs
Home-page: https://github.com/tlittenberg/lisacattools
Author: James I. Thorpe, Tyson B. Littenberg, Jean-Christophe Malapert
Author-email: tyson.b.littenberg@nasa.gov
License: GPLV3
Classifier: Programming Language :: Python :: 3
Classifier: License :: OSI Approved :: GNU General Public License v3 (GPLv3)
Classifier: Operating System :: OS Independent
Requires-Python: >=3.8
License-File: LICENSE
Requires-Dist: astropy (==5.2.1)
Requires-Dist: corner (==2.2.1)
Requires-Dist: healpy (==1.16.2)
Requires-Dist: ligo.skymap (==1.0.4)
Requires-Dist: matplotlib (==3.6.3)
Requires-Dist: pandas (==1.5.2)
Requires-Dist: seaborn (==0.12.2)
Requires-Dist: tables (==3.8.0)
